midea/__init__.py
midea/client.py
midea/cloud.py
midea/command.py
midea/crc8.py
midea/device.py
midea/packet_builder.py
midea/security.py
midea-0.1.7.dist-info/DESCRIPTION.rst
midea-0.1.7.dist-info/METADATA
midea-0.1.7.dist-info/RECORD
midea-0.1.7.dist-info/WHEEL
midea-0.1.7.dist-info/metadata.json
midea-0.1.7.dist-info/top_level.txt
