Metadata-Version: 2.0
Name: midea
Version: 0.1.7
Summary: A library to control Midea appliances via the cloud API
Home-page: https://github.com/NeoAcheron/midea-ac-py
Author: NeoAcheron
Author-email: master@neoacheron.com
License: UNKNOWN
Platform: UNKNOWN
Classifier: Programming Language :: Python :: 3
Classifier: License :: OSI Approved :: MIT License
Classifier: Operating System :: OS Independent
